MANIFEST.in
README.rst
nocrux.py
setup.py
nocrux.egg-info/PKG-INFO
nocrux.egg-info/SOURCES.txt
nocrux.egg-info/dependency_links.txt
nocrux.egg-info/entry_points.txt
nocrux.egg-info/requires.txt
nocrux.egg-info/top_level.txt