Metadata-Version: 1.0
Name: nocrux
Version: 2.0.3
Summary: a painless per-user daemon manager
Home-page: https://github.com/NiklasRosenstein/nocrux
Author: Niklas Rosenstein
Author-email: rosensteinniklas@gmail.com
License: UNKNOWN
Platform: UNKNOWN
